hanzi_pinyin/__init__.py
hanzi_pinyin/dict.json
hanzi_pinyin/lib.py
hanzi_pinyin-0.2.8.dist-info/METADATA
hanzi_pinyin-0.2.8.dist-info/WHEEL
hanzi_pinyin-0.2.8.dist-info/top_level.txt
hanzi_pinyin-0.2.8.dist-info/RECORD
